MixPage/__init__.py
MixPage/base.py
MixPage/base.pyi
MixPage/configs.ini
MixPage/drission.py
MixPage/drission.pyi
MixPage/driver_element.py
MixPage/driver_element.pyi
MixPage/driver_options.py
MixPage/driver_options.pyi
MixPage/driver_page.py
MixPage/driver_page.pyi
MixPage/easy_set.py
MixPage/easy_set.pyi
MixPage/mix_page.py
MixPage/mix_page.pyi
MixPage/options_manage.py
MixPage/options_manage.pyi
MixPage/session_element.py
MixPage/session_element.pyi
MixPage/session_options.py
MixPage/session_options.pyi
MixPage/session_page.py
MixPage/session_page.pyi
MixPage/shadow_root_element.py
MixPage/shadow_root_element.pyi
MixPage-1.0.3.dist-info/LICENSE
MixPage-1.0.3.dist-info/METADATA
MixPage-1.0.3.dist-info/WHEEL
MixPage-1.0.3.dist-info/top_level.txt
MixPage-1.0.3.dist-info/RECORD
